{
"meta":{"test_sets":[],"test_metrics":[],"learn_metrics":[{"best_value":"Min","name":"RMSE"}],"launch_mode":"Train","parameters":"","iteration_count":200,"learn_sets":["learn"],"name":"experiment"},
"iterations":[
{"learn":[13.02385887],"iteration":0,"passed_time":0.05654254295,"remaining_time":11.25196605},
{"learn":[11.42511277],"iteration":1,"passed_time":0.05718550557,"remaining_time":5.661365051},
{"learn":[10.16390588],"iteration":2,"passed_time":0.0577115924,"remaining_time":3.789727901},
{"learn":[9.117386422],"iteration":3,"passed_time":0.05830134633,"remaining_time":2.85676597},
{"learn":[8.320784796],"iteration":4,"passed_time":0.05877205779,"remaining_time":2.292110254},
{"learn":[7.729384055],"iteration":5,"passed_time":0.05932589481,"remaining_time":1.918203932},
{"learn":[7.215303239],"iteration":6,"passed_time":0.05971593907,"remaining_time":1.646453749},
{"learn":[6.825535256],"iteration":7,"passed_time":0.06030548466,"remaining_time":1.447331632},
{"learn":[6.443076698],"iteration":8,"passed_time":0.06079873795,"remaining_time":1.290284328},
{"learn":[6.190897061],"iteration":9,"passed_time":0.06124382424,"remaining_time":1.163632661},
{"learn":[5.976342535],"iteration":10,"passed_time":0.06181466137,"remaining_time":1.062088273},
{"learn":[5.806594266],"iteration":11,"passed_time":0.06235637331,"remaining_time":0.9769165152},
{"learn":[5.689884527],"iteration":12,"passed_time":0.06285337662,"remaining_time":0.9041216483},
{"learn":[5.599198351],"iteration":13,"passed_time":0.06414580189,"remaining_time":0.8522227965},
{"learn":[5.491718054],"iteration":14,"passed_time":0.06467201372,"remaining_time":0.7976215026},
{"learn":[5.423030935],"iteration":15,"passed_time":0.06514864189,"remaining_time":0.7492093818},
{"learn":[5.352431646],"iteration":16,"passed_time":0.06567852042,"remaining_time":0.7070099551},
{"learn":[5.295585625],"iteration":17,"passed_time":0.06615177357,"remaining_time":0.6688679328},
{"learn":[5.25564638],"iteration":18,"passed_time":0.06657994309,"remaining_time":0.6342615631},
{"learn":[5.212556243],"iteration":19,"passed_time":0.06711252996,"remaining_time":0.6040127697},
{"learn":[5.177754333],"iteration":20,"passed_time":0.06767549204,"remaining_time":0.5768530036},
{"learn":[5.156747151],"iteration":21,"passed_time":0.06817837039,"remaining_time":0.5516249968},
{"learn":[5.130184816],"iteration":22,"passed_time":0.068570248,"remaining_time":0.5276927781},
{"learn":[5.102908484],"iteration":23,"passed_time":0.06897279234,"remaining_time":0.5058004772},
{"learn":[5.081278407],"iteration":24,"passed_time":0.06940246187,"remaining_time":0.4858172331},
{"learn":[5.067951738],"iteration":25,"passed_time":0.06981733963,"remaining_time":0.4672391191},
{"learn":[5.045111437],"iteration":26,"passed_time":0.0702628426,"remaining_time":0.4502026581},
{"learn":[5.025524162],"iteration":27,"passed_time":0.07072080398,"remaining_time":0.4344277959},
{"learn":[4.991775853],"iteration":28,"passed_time":0.07116884863,"remaining_time":0.4196507971},
{"learn":[4.975927465],"iteration":29,"passed_time":0.07156130957,"remaining_time":0.4055140876},
{"learn":[4.955713172],"iteration":30,"passed_time":0.07201789594,"remaining_time":0.3926136908},
{"learn":[4.929667053],"iteration":31,"passed_time":0.07249919081,"remaining_time":0.3806207518},
{"learn":[4.91860801],"iteration":32,"passed_time":0.07294898547,"remaining_time":0.369166078},
{"learn":[4.909563306],"iteration":33,"passed_time":0.07341511357,"remaining_time":0.3584384957},
{"learn":[4.897199239],"iteration":34,"passed_time":0.07383228302,"remaining_time":0.3480664771},
{"learn":[4.882001097],"iteration":35,"passed_time":0.0742651609,"remaining_time":0.3383190663},
{"learn":[4.872154701],"iteration":36,"passed_time":0.07473808071,"remaining_time":0.3292515448},
{"learn":[4.851168422],"iteration":37,"passed_time":0.07517570862,"remaining_time":0.3204859157},
{"learn":[4.836898819],"iteration":38,"passed_time":0.07568512868,"remaining_time":0.3124437363},
{"learn":[4.809588493],"iteration":39,"passed_time":0.07610729816,"remaining_time":0.3044291926},
{"learn":[4.790509552],"iteration":40,"passed_time":0.07656767622,"remaining_time":0.2969331834},
{"learn":[4.770956281],"iteration":41,"passed_time":0.07700001243,"remaining_time":0.2896667134},
{"learn":[4.755950455],"iteration":42,"passed_time":0.07743997369,"remaining_time":0.2827459505},
{"learn":[4.753120963],"iteration":43,"passed_time":0.07786960155,"remaining_time":0.2760831328},
{"learn":[4.743009115],"iteration":44,"passed_time":0.07825360411,"remaining_time":0.2695401919},
{"learn":[4.700313486],"iteration":45,"passed_time":0.07874164902,"remaining_time":0.2636133467},
{"learn":[4.686124085],"iteration":46,"passed_time":0.07922436057,"remaining_time":0.257900578},
{"learn":[4.672473048],"iteration":47,"passed_time":0.07962444656,"remaining_time":0.2521440808},
{"learn":[4.65757743],"iteration":48,"passed_time":0.08001953253,"remaining_time":0.2465908043},
{"learn":[4.640987545],"iteration":49,"passed_time":0.08045224374,"remaining_time":0.2413567312},
{"learn":[4.628551108],"iteration":50,"passed_time":0.0809124968,"remaining_time":0.2363914122},
{"learn":[4.618820602],"iteration":51,"passed_time":0.0814184585,"remaining_time":0.2317294588},
{"learn":[4.59084703],"iteration":52,"passed_time":0.08189408667,"remaining_time":0.2271402026},
{"learn":[4.549247995],"iteration":53,"passed_time":0.08230650608,"remaining_time":0.2225324053},
{"learn":[4.531630872],"iteration":54,"passed_time":0.08274242565,"remaining_time":0.2181391222},
{"learn":[4.516548561],"iteration":55,"passed_time":0.08318955362,"remaining_time":0.213915995},
{"learn":[4.505589614],"iteration":56,"passed_time":0.08363905661,"remaining_time":0.2098313175},
{"learn":[4.489003542],"iteration":57,"passed_time":0.08418647692,"remaining_time":0.2061117194},
{"learn":[4.487626699],"iteration":58,"passed_time":0.08458493791,"remaining_time":0.2021436652},
{"learn":[4.475007748],"iteration":59,"passed_time":0.08510444137,"remaining_time":0.1985770299},
{"learn":[4.458138988],"iteration":60,"passed_time":0.08552236081,"remaining_time":0.1948788222},
{"learn":[4.456280641],"iteration":61,"passed_time":0.08604198927,"remaining_time":0.1915128148},
{"learn":[4.447305736],"iteration":62,"passed_time":0.08650057566,"remaining_time":0.1881044264},
{"learn":[4.42377596],"iteration":63,"passed_time":0.08695366201,"remaining_time":0.1847765318},
{"learn":[4.41521751],"iteration":64,"passed_time":0.08751374907,"remaining_time":0.181759325},
{"learn":[4.391010319],"iteration":65,"passed_time":0.08793229352,"remaining_time":0.178529202},
{"learn":[4.387783042],"iteration":66,"passed_time":0.088354588,"remaining_time":0.1753904508},
{"learn":[4.373327319],"iteration":67,"passed_time":0.08881388272,"remaining_time":0.1724034194},
{"learn":[4.353742688],"iteration":68,"passed_time":0.08936030302,"remaining_time":0.1696550681},
{"learn":[4.352403352],"iteration":69,"passed_time":0.08988763986,"remaining_time":0.1669341883},
{"learn":[4.349648561],"iteration":70,"passed_time":0.09034939294,"remaining_time":0.1641559393},
{"learn":[4.345052583],"iteration":71,"passed_time":0.09078427083,"remaining_time":0.1613942593},
{"learn":[4.32395265],"iteration":72,"passed_time":0.09119885692,"remaining_time":0.1586610251},
{"learn":[4.306717475],"iteration":73,"passed_time":0.09168277681,"remaining_time":0.1561085119},
{"learn":[4.299386032],"iteration":74,"passed_time":0.09214590489,"remaining_time":0.1535765082},
{"learn":[4.276154368],"iteration":75,"passed_time":0.09264944991,"remaining_time":0.151164892},
{"learn":[4.2643267],"iteration":76,"passed_time":0.09310649462,"remaining_time":0.1487285563},
{"learn":[4.243679007],"iteration":77,"passed_time":0.09354224752,"remaining_time":0.1463096692},
{"learn":[4.216616171],"iteration":78,"passed_time":0.09397950043,"remaining_time":0.1439432855},
{"learn":[4.188830599],"iteration":79,"passed_time":0.0944456702,"remaining_time":0.1416685053},
{"learn":[4.171309905],"iteration":80,"passed_time":0.09495221524,"remaining_time":0.1394976989},
{"learn":[4.170950987],"iteration":81,"passed_time":0.09537113469,"remaining_time":0.1372413889},
{"learn":[4.156249784],"iteration":82,"passed_time":0.09579513751,"remaining_time":0.1350365191},
{"learn":[4.147740387],"iteration":83,"passed_time":0.09621522364,"remaining_time":0.1328686422},
{"learn":[4.136343283],"iteration":84,"passed_time":0.09665797659,"remaining_time":0.1307725566},
{"learn":[4.128142981],"iteration":85,"passed_time":0.09713893812,"remaining_time":0.1287655691},
{"learn":[4.108353935],"iteration":86,"passed_time":0.09757202434,"remaining_time":0.1267314799},
{"learn":[4.078423196],"iteration":87,"passed_time":0.09799069379,"remaining_time":0.1247154285},
{"learn":[4.063729803],"iteration":88,"passed_time":0.09848940544,"remaining_time":0.1228351012},
{"learn":[4.056260109],"iteration":89,"passed_time":0.09896836696,"remaining_time":0.1209613374},
{"learn":[4.044999209],"iteration":90,"passed_time":0.09946262025,"remaining_time":0.1191365451},
{"learn":[4.031691737],"iteration":91,"passed_time":0.09999958216,"remaining_time":0.1173908138},
{"learn":[4.020890127],"iteration":92,"passed_time":0.1004479601,"remaining_time":0.1155691584},
{"learn":[3.993862513],"iteration":93,"passed_time":0.1009338384,"remaining_time":0.1138190092},
{"learn":[3.972058385],"iteration":94,"passed_time":0.1014725086,"remaining_time":0.1121538253},
{"learn":[3.958049519],"iteration":95,"passed_time":0.1019849287,"remaining_time":0.1104836728},
{"learn":[3.956576572],"iteration":96,"passed_time":0.1025015571,"remaining_time":0.1088418596},
{"learn":[3.94607992],"iteration":97,"passed_time":0.102975352,"remaining_time":0.1071784276},
{"learn":[3.941330992],"iteration":98,"passed_time":0.1033800213,"remaining_time":0.1054685066},
{"learn":[3.93335512],"iteration":99,"passed_time":0.1038312327,"remaining_time":0.1038312327},
{"learn":[3.921720825],"iteration":100,"passed_time":0.1042090685,"remaining_time":0.1021455226},
{"learn":[3.890274907],"iteration":101,"passed_time":0.1046654465,"remaining_time":0.1005609192},
{"learn":[3.881831316],"iteration":102,"passed_time":0.1050925744,"remaining_time":0.09897067685},
{"learn":[3.871892151],"iteration":103,"passed_time":0.1055742859,"remaining_time":0.09745318701},
{"learn":[3.843919595],"iteration":104,"passed_time":0.1060328306,"remaining_time":0.09593446582},
{"learn":[3.842239465],"iteration":105,"passed_time":0.1064461251,"remaining_time":0.09439562034},
{"learn":[3.836202684],"iteration":106,"passed_time":0.1069236282,"remaining_time":0.09293362081},
{"learn":[3.815052304],"iteration":107,"passed_time":0.1073387143,"remaining_time":0.09143668258},
{"learn":[3.798363152],"iteration":108,"passed_time":0.1078499677,"remaining_time":0.09003988132},
{"learn":[3.788185955],"iteration":109,"passed_time":0.1082611371,"remaining_time":0.08857729402},
{"learn":[3.783800975],"iteration":110,"passed_time":0.1088992664,"remaining_time":0.087315628},
{"learn":[3.770532439],"iteration":111,"passed_time":0.1093801029,"remaining_time":0.08594150944},
{"learn":[3.751956347],"iteration":112,"passed_time":0.1099783986,"remaining_time":0.0846736343},
{"learn":[3.742735967],"iteration":113,"passed_time":0.1103906096,"remaining_time":0.08327712657},
{"learn":[3.739190076],"iteration":114,"passed_time":0.1109846553,"remaining_time":0.0820321365},
{"learn":[3.717052261],"iteration":115,"passed_time":0.1115448257,"remaining_time":0.08077383927},
{"learn":[3.705123174],"iteration":116,"passed_time":0.1120279539,"remaining_time":0.07947282198},
{"learn":[3.69375033],"iteration":117,"passed_time":0.1124871236,"remaining_time":0.07816901809},
{"learn":[3.688233714],"iteration":118,"passed_time":0.1129894603,"remaining_time":0.07690879229},
{"learn":[3.674773858],"iteration":119,"passed_time":0.1134820886,"remaining_time":0.0756547257},
{"learn":[3.673878182],"iteration":120,"passed_time":0.1139493833,"remaining_time":0.07439670482},
{"learn":[3.671889482],"iteration":121,"passed_time":0.114353011,"remaining_time":0.07311094147},
{"learn":[3.65682075],"iteration":122,"passed_time":0.1148498893,"remaining_time":0.07189789819},
{"learn":[3.644042562],"iteration":123,"passed_time":0.1153303509,"remaining_time":0.07068634407},
{"learn":[3.631399389],"iteration":124,"passed_time":0.1157582287,"remaining_time":0.06945493722},
{"learn":[3.612954906],"iteration":125,"passed_time":0.1161712731,"remaining_time":0.0682275731},
{"learn":[3.609486884],"iteration":126,"passed_time":0.1167597354,"remaining_time":0.06711386363},
{"learn":[3.59672855],"iteration":127,"passed_time":0.1172610304,"remaining_time":0.06595932958},
{"learn":[3.591964384],"iteration":128,"passed_time":0.1177719921,"remaining_time":0.06482024371},
{"learn":[3.586421003],"iteration":129,"passed_time":0.1182489536,"remaining_time":0.06367251348},
{"learn":[3.576486273],"iteration":130,"passed_time":0.1186949566,"remaining_time":0.06251871759},
{"learn":[3.575541489],"iteration":131,"passed_time":0.1191967932,"remaining_time":0.06140440864},
{"learn":[3.571727806],"iteration":132,"passed_time":0.1196387545,"remaining_time":0.06026914702},
{"learn":[3.566933849],"iteration":133,"passed_time":0.1200840075,"remaining_time":0.05914585443},
{"learn":[3.552041293],"iteration":134,"passed_time":0.1205884692,"remaining_time":0.05806111479},
{"learn":[3.543645619],"iteration":135,"passed_time":0.1212263484,"remaining_time":0.05704769338},
{"learn":[3.525104519],"iteration":136,"passed_time":0.1216742264,"remaining_time":0.05595238148},
{"learn":[3.52078168],"iteration":137,"passed_time":0.1221013126,"remaining_time":0.05485711145},
{"learn":[3.50840345],"iteration":138,"passed_time":0.1225424405,"remaining_time":0.05377761778},
{"learn":[3.50798482],"iteration":139,"passed_time":0.1229656517,"remaining_time":0.052699565},
{"learn":[3.499557215],"iteration":140,"passed_time":0.1234189047,"remaining_time":0.05164337146},
{"learn":[3.498324417],"iteration":141,"passed_time":0.1238772411,"remaining_time":0.05059774635},
{"learn":[3.486669735],"iteration":142,"passed_time":0.1243444108,"remaining_time":0.04956385607},
{"learn":[3.481813529],"iteration":143,"passed_time":0.1247523719,"remaining_time":0.04851481129},
{"learn":[3.467614006],"iteration":144,"passed_time":0.1252322917,"remaining_time":0.04750190377},
{"learn":[3.462773822],"iteration":145,"passed_time":0.1256822947,"remaining_time":0.0464852323},
{"learn":[3.453278566],"iteration":146,"passed_time":0.1261387978,"remaining_time":0.04547861417},
{"learn":[3.436426195],"iteration":147,"passed_time":0.1265970925,"remaining_time":0.04448005953},
{"learn":[3.435880141],"iteration":148,"passed_time":0.1270253453,"remaining_time":0.04347847391},
{"learn":[3.424309956],"iteration":149,"passed_time":0.1275109319,"remaining_time":0.04250364397},
{"learn":[3.418990953],"iteration":150,"passed_time":0.1280310187,"remaining_time":0.04154648951},
{"learn":[3.416108078],"iteration":151,"passed_time":0.1284756883,"remaining_time":0.04057127},
{"learn":[3.413119515],"iteration":152,"passed_time":0.128926233,"remaining_time":0.03960479053},
{"learn":[3.409683342],"iteration":153,"passed_time":0.1293422358,"remaining_time":0.0386346938},
{"learn":[3.404361351],"iteration":154,"passed_time":0.1297551552,"remaining_time":0.0376708515},
{"learn":[3.398207252],"iteration":155,"passed_time":0.1302444501,"remaining_time":0.03673561413},
{"learn":[3.395943767],"iteration":156,"passed_time":0.1307441201,"remaining_time":0.03580889913},
{"learn":[3.388683369],"iteration":157,"passed_time":0.1312208316,"remaining_time":0.03488148688},
{"learn":[3.373003803],"iteration":158,"passed_time":0.1316727096,"remaining_time":0.03395334021},
{"learn":[3.371650359],"iteration":159,"passed_time":0.1321235043,"remaining_time":0.03303087607},
{"learn":[3.360890675],"iteration":160,"passed_time":0.1326444661,"remaining_time":0.03213126818},
{"learn":[3.342831516],"iteration":161,"passed_time":0.133139636,"remaining_time":0.031230285},
{"learn":[3.336472345],"iteration":162,"passed_time":0.1336885147,"remaining_time":0.03034647266},
{"learn":[3.324100341],"iteration":163,"passed_time":0.1341019341,"remaining_time":0.02943700993},
{"learn":[3.315695919],"iteration":164,"passed_time":0.1345167285,"remaining_time":0.02853385151},
{"learn":[3.314462393],"iteration":165,"passed_time":0.1348998144,"remaining_time":0.02763008247},
{"learn":[3.311413783],"iteration":166,"passed_time":0.1354049011,"remaining_time":0.02675665711},
{"learn":[3.303291704],"iteration":167,"passed_time":0.135844529,"remaining_time":0.02587514839},
{"learn":[3.280791096],"iteration":168,"passed_time":0.1363559074,"remaining_time":0.02501203036},
{"learn":[3.272853161],"iteration":169,"passed_time":0.1368241189,"remaining_time":0.02414543275},
{"learn":[3.258621674],"iteration":170,"passed_time":0.1373258306,"remaining_time":0.02328917594},
{"learn":[3.246560612],"iteration":171,"passed_time":0.137843334,"remaining_time":0.02243961251},
{"learn":[3.230191296],"iteration":172,"passed_time":0.1383075871,"remaining_time":0.02158557718},
{"learn":[3.225527154],"iteration":173,"passed_time":0.1387656318,"remaining_time":0.02073509441},
{"learn":[3.223758232],"iteration":174,"passed_time":0.1392878436,"remaining_time":0.01989826337},
{"learn":[3.217547618],"iteration":175,"passed_time":0.1397522217,"remaining_time":0.01905712114},
{"learn":[3.21370528],"iteration":176,"passed_time":0.1402062247,"remaining_time":0.01821888796},
{"learn":[3.208785771],"iteration":177,"passed_time":0.1406653945,"remaining_time":0.01738561055},
{"learn":[3.200078054],"iteration":178,"passed_time":0.1411548144,"remaining_time":0.01656006202},
{"learn":[3.187515002],"iteration":179,"passed_time":0.141599234,"remaining_time":0.01573324822},
{"learn":[3.177318153],"iteration":180,"passed_time":0.1420364869,"remaining_time":0.01490990747},
{"learn":[3.166053042],"iteration":181,"passed_time":0.1425016983,"remaining_time":0.01409357456},
{"learn":[3.152188937],"iteration":182,"passed_time":0.1430395769,"remaining_time":0.01328782955},
{"learn":[3.140922732],"iteration":183,"passed_time":0.1435784555,"remaining_time":0.01248508309},
{"learn":[3.131021096],"iteration":184,"passed_time":0.1440234168,"remaining_time":0.01167757434},
{"learn":[3.125454648],"iteration":185,"passed_time":0.1445005866,"remaining_time":0.01087638824},
{"learn":[3.112421681],"iteration":186,"passed_time":0.145011965,"remaining_time":0.0100810457},
{"learn":[3.111545202],"iteration":187,"passed_time":0.1454973016,"remaining_time":0.009287061805},
{"learn":[3.111265963],"iteration":188,"passed_time":0.1459843882,"remaining_time":0.008496445873},
{"learn":[3.10675176],"iteration":189,"passed_time":0.146458808,"remaining_time":0.007708358316},
{"learn":[3.105957559],"iteration":190,"passed_time":0.1469471863,"remaining_time":0.006924212965},
{"learn":[3.096354432],"iteration":191,"passed_time":0.1474451896,"remaining_time":0.006143549566},
{"learn":[3.091539139],"iteration":192,"passed_time":0.1479113593,"remaining_time":0.005364660702},
{"learn":[3.078181215],"iteration":193,"passed_time":0.1484011959,"remaining_time":0.004589727709},
{"learn":[3.073481078],"iteration":194,"passed_time":0.1488926992,"remaining_time":0.003817761518},
{"learn":[3.069656861],"iteration":195,"passed_time":0.149418036,"remaining_time":0.003049347674},
{"learn":[3.064934285],"iteration":196,"passed_time":0.1499336645,"remaining_time":0.002283253774},
{"learn":[3.059277934],"iteration":197,"passed_time":0.1503611256,"remaining_time":0.001518799249},
{"learn":[3.057639683],"iteration":198,"passed_time":0.1508497122,"remaining_time":0.0007580387549},
{"learn":[3.047205523],"iteration":199,"passed_time":0.1513669657,"remaining_time":0}
]}